github_dl.py
download/__init__.py
download/download_gists.py
download/download_repos.py
download/public_gists.py
download/search_repos.py
download/setup_github.py
download/user_gists.py
github_dl-0.1a9.dist-info/DESCRIPTION.rst
github_dl-0.1a9.dist-info/METADATA
github_dl-0.1a9.dist-info/RECORD
github_dl-0.1a9.dist-info/WHEEL
github_dl-0.1a9.dist-info/entry_points.txt
github_dl-0.1a9.dist-info/metadata.json
github_dl-0.1a9.dist-info/top_level.txt
