Metadata-Version: 2.0
Name: github-dl
Version: 0.1a9
Summary: a command line tool for downloading repositories and gists
Home-page: https://github.com/cameres/github-dl
Author: Connor Ameres
Author-email: connorameres@gmail.com
License: Mozilla Public License 2.0 (MPL 2.0)
Keywords: github gists download
Platform: UNKNOWN
Classifier: Development Status :: 3 - Alpha
Classifier: License :: OSI Approved :: Mozilla Public License 2.0 (MPL 2.0)
Classifier: Topic :: Software Development
Classifier: Programming Language :: Python :: 2.7
Classifier: Programming Language :: Python :: 3.5
Requires-Dist: click
Requires-Dist: gitpython
Requires-Dist: pygithub
Requires-Dist: requests
